README.md
requirements.txt
pysgconnect/__init__.py
pysgconnect/sg_connect_auth.py
pysgconnect/token.py
pysgconnect-2.3.dist-info/LICENSE
pysgconnect-2.3.dist-info/METADATA
pysgconnect-2.3.dist-info/WHEEL
pysgconnect-2.3.dist-info/top_level.txt
pysgconnect-2.3.dist-info/RECORD
